<bpy>
  <Theme>
    <user_interface>
      <ThemeUserInterface
        menu_shadow_fac="0.4"
        menu_shadow_width="2"
        icon_alpha="1"
        icon_saturation="0.5"
        widget_emboss="#FFFFFF"
        editor_outline="#FFFFFF"
        widget_text_cursor="#FFFFFF"
        panel_roundness="0.4"
        transparent_checker_primary="#FFFFFF"
        transparent_checker_secondary="#FFFFFF"
        transparent_checker_size="8"
        axis_x="#FFFFFF"
        axis_y="#FFFFFF"
        axis_z="#FFFFFF"
        gizmo_hi="#FFFFFF"
        gizmo_primary="#FFFFFF"
        gizmo_secondary="#FFFFFF"
        gizmo_view_align="#FFFFFF"
        gizmo_a="#FFFFFF"
        gizmo_b="#FFFFFF"
        icon_scene="#FFFFFF"
        icon_collection="#FFFFFF"
        icon_object="#FFFFFF"
        icon_object_data="#FFFFFF"
        icon_modifier="#FFFFFF"
        icon_shading="#FFFFFF"
        icon_folder="#FFFFFF"
        icon_border_intensity="0"
        >
        <wcol_regular>
          <ThemeWidgetColors
            outline="#FFFFFF"
            inner="#FFFFFF"
            inner_sel="#FFFFFF"
            item="#FFFFFF"
            text="#FFFFFF"
            text_sel="#FFFFFF"
            show_shaded="FALSE"
            shadetop="0"
            shadedown="0"
            roundness="0.4"
            >
          </ThemeWidgetColors>
        </wcol_regular>
        <wcol_tool>
          <ThemeWidgetColors
            outline="#FFFFFF"
            inner="#FFFFFF"
            inner_sel="#FFFFFF"
            item="#FFFFFF"
            text="#FFFFFF"
            text_sel="#FFFFFF"
            show_shaded="FALSE"
            shadetop="0"
            shadedown="0"
            roundness="0.4"
            >
          </ThemeWidgetColors>
        </wcol_tool>
        <wcol_toolbar_item>
          <ThemeWidgetColors
            outline="#FFFFFF"
            inner="#FFFFFF"
            inner_sel="#FFFFFF"
            item="#FFFFFF"
            text="#FFFFFF"
            text_sel="#FFFFFF"
            show_shaded="FALSE"
            shadetop="0"
            shadedown="0"
            roundness="0.4"
            >
          </ThemeWidgetColors>
        </wcol_toolbar_item>
        <wcol_radio>
          <ThemeWidgetColors
            outline="#FFFFFF"
            inner="#FFFFFF"
            inner_sel="#FFFFFF"
            item="#FFFFFF"
            text="#FFFFFF"
            text_sel="#FFFFFF"
            show_shaded="FALSE"
            shadetop="0"
            shadedown="0"
            roundness="0.4"
            >
          </ThemeWidgetColors>
        </wcol_radio>
        <wcol_text>
          <ThemeWidgetColors
            outline="#FFFFFF"
            inner="#FFFFFF"
            inner_sel="#FFFFFF"
            item="#FFFFFF"
            text="#FFFFFF"
            text_sel="#FFFFFF"
            show_shaded="FALSE"
            shadetop="0"
            shadedown="0"
            roundness="0.4"
            >
          </ThemeWidgetColors>
        </wcol_text>
        <wcol_option>
          <ThemeWidgetColors
            outline="#FFFFFF"
            inner="#FFFFFF"
            inner_sel="#FFFFFF"
            item="#FFFFFF"
            text="#FFFFFF"
            text_sel="#FFFFFF"
            show_shaded="FALSE"
            shadetop="0"
            shadedown="0"
            roundness="0.4"
            >
          </ThemeWidgetColors>
        </wcol_option>
        <wcol_toggle>
          <ThemeWidgetColors
            outline="#FFFFFF"
            inner="#FFFFFF"
            inner_sel="#FFFFFF"
            item="#FFFFFF"
            text="#FFFFFF"
            text_sel="#FFFFFF"
            show_shaded="FALSE"
            shadetop="0"
            shadedown="0"
            roundness="0.4"
            >
          </ThemeWidgetColors>
        </wcol_toggle>
        <wcol_num>
          <ThemeWidgetColors
            outline="#FFFFFF"
            inner="#FFFFFF"
            inner_sel="#FFFFFF"
            item="#FFFFFF"
            text="#FFFFFF"
            text_sel="#FFFFFF"
            show_shaded="FALSE"
            shadetop="0"
            shadedown="0"
            roundness="0.4"
            >
          </ThemeWidgetColors>
        </wcol_num>
        <wcol_numslider>
          <ThemeWidgetColors
            outline="#FFFFFF"
            inner="#FFFFFF"
            inner_sel="#FFFFFF"
            item="#FFFFFF"
            text="#FFFFFF"
            text_sel="#FFFFFF"
            show_shaded="FALSE"
            shadetop="0"
            shadedown="0"
            roundness="0.4"
            >
          </ThemeWidgetColors>
        </wcol_numslider>
        <wcol_box>
          <ThemeWidgetColors
            outline="#FFFFFF"
            inner="#FFFFFF"
            inner_sel="#FFFFFF"
            item="#FFFFFF"
            text="#FFFFFF"
            text_sel="#FFFFFF"
            show_shaded="FALSE"
            shadetop="0"
            shadedown="0"
            roundness="0.4"
            >
          </ThemeWidgetColors>
        </wcol_box>
        <wcol_menu>
          <ThemeWidgetColors
            outline="#FFFFFF"
            inner="#FFFFFF"
            inner_sel="#FFFFFF"
            item="#FFFFFF"
            text="#FFFFFF"
            text_sel="#FFFFFF"
            show_shaded="FALSE"
            shadetop="0"
            shadedown="0"
            roundness="0.4"
            >
          </ThemeWidgetColors>
        </wcol_menu>
        <wcol_pulldown>
          <ThemeWidgetColors
            outline="#FFFFFF"
            inner="#FFFFFF"
            inner_sel="#FFFFFF"
            item="#FFFFFF"
            text="#FFFFFF"
            text_sel="#FFFFFF"
            show_shaded="FALSE"
            shadetop="0"
            shadedown="0"
            roundness="0.4"
            >
          </ThemeWidgetColors>
        </wcol_pulldown>
        <wcol_menu_back>
          <ThemeWidgetColors
            outline="#FFFFFF"
            inner="#FFFFFF"
            inner_sel="#FFFFFF"
            item="#FFFFFF"
            text="#FFFFFF"
            text_sel="#FFFFFF"
            show_shaded="FALSE"
            shadetop="0"
            shadedown="0"
            roundness="0.4"
            >
          </ThemeWidgetColors>
        </wcol_menu_back>
        <wcol_pie_menu>
          <ThemeWidgetColors
            outline="#FFFFFF"
            inner="#FFFFFF"
            inner_sel="#FFFFFF"
            item="#FFFFFF"
            text="#FFFFFF"
            text_sel="#FFFFFF"
            show_shaded="FALSE"
            shadetop="0"
            shadedown="0"
            roundness="0.4"
            >
          </ThemeWidgetColors>
        </wcol_pie_menu>
        <wcol_tooltip>
          <ThemeWidgetColors
            outline="#FFFFFF"
            inner="#FFFFFF"
            inner_sel="#FFFFFF"
            item="#FFFFFF"
            text="#FFFFFF"
            text_sel="#FFFFFF"
            show_shaded="FALSE"
            shadetop="0"
            shadedown="0"
            roundness="0.4"
            >
          </ThemeWidgetColors>
        </wcol_tooltip>
        <wcol_menu_item>
          <ThemeWidgetColors
            outline="#FFFFFF"
            inner="#FFFFFF"
            inner_sel="#FFFFFF"
            item="#FFFFFF"
            text="#FFFFFF"
            text_sel="#FFFFFF"
            show_shaded="FALSE"
            shadetop="0"
            shadedown="0"
            roundness="0.4"
            >
          </ThemeWidgetColors>
        </wcol_menu_item>
        <wcol_scroll>
          <ThemeWidgetColors
            outline="#FFFFFF"
            inner="#FFFFFF"
            inner_sel="#FFFFFF"
            item="#FFFFFF"
            text="#FFFFFF"
            text_sel="#FFFFFF"
            show_shaded="FALSE"
            shadetop="0"
            shadedown="0"
            roundness="1"
            >
          </ThemeWidgetColors>
        </wcol_scroll>
        <wcol_progress>
          <ThemeWidgetColors
            outline="#FFFFFF"
            inner="#FFFFFF"
            inner_sel="#FFFFFF"
            item="#FFFFFF"
            text="#FFFFFF"
            text_sel="#FFFFFF"
            show_shaded="FALSE"
            shadetop="0"
            shadedown="0"
            roundness="0.4"
            >
          </ThemeWidgetColors>
        </wcol_progress>
        <wcol_list_item>
          <ThemeWidgetColors
            outline="#FFFFFF"
            inner="#FFFFFF"
            inner_sel="#FFFFFF"
            item="#FFFFFF"
            text="#FFFFFF"
            text_sel="#FFFFFF"
            show_shaded="FALSE"
            shadetop="0"
            shadedown="0"
            roundness="0.4"
            >
          </ThemeWidgetColors>
        </wcol_list_item>
        <wcol_view_item>
          <ThemeWidgetColors
            outline="#FFFFFF"
            inner="#FFFFFF"
            inner_sel="#FFFFFF"
            item="#FFFFFF"
            text="#FFFFFF"
            text_sel="#FFFFFF"
            show_shaded="FALSE"
            shadetop="0"
            shadedown="0"
            roundness="0.4"
            >
          </ThemeWidgetColors>
        </wcol_view_item>
        <wcol_state>
          <ThemeWidgetStateColors
            inner_anim="#FFFFFF"
            inner_anim_sel="#FFFFFF"
            inner_key="#FFFFFF"
            inner_key_sel="#FFFFFF"
            inner_driven="#FFFFFF"
            inner_driven_sel="#FFFFFF"
            inner_overridden="#FFFFFF"
            inner_overridden_sel="#FFFFFF"
            inner_changed="#FFFFFF"
            inner_changed_sel="#FFFFFF"
            blend="0.5"
            >
          </ThemeWidgetStateColors>
        </wcol_state>
        <wcol_tab>
          <ThemeWidgetColors
            outline="#FFFFFF"
            inner="#FFFFFF"
            inner_sel="#FFFFFF"
            item="#FFFFFF"
            text="#FFFFFF"
            text_sel="#FFFFFF"
            show_shaded="FALSE"
            shadetop="0"
            shadedown="0"
            roundness="0.4"
            >
          </ThemeWidgetColors>
        </wcol_tab>
      </ThemeUserInterface>
    </user_interface>
    <view_3d>
      <ThemeView3D
        grid="#FFFFFF"
        clipping_border_3d="#FFFFFF"
        wire="#FFFFFF"
        wire_edit="#FFFFFF"
        edge_width="1"
        gp_vertex="#FFFFFF"
        gp_vertex_select="#FFFFFF"
        gp_vertex_size="3"
        text_grease_pencil="#FFFFFF"
        object_selected="#FFFFFF"
        object_active="#FFFFFF"
        text_keyframe="#FFFFFF"
        camera="#FFFFFF"
        empty="#FFFFFF"
        light="#FFFFFF"
        speaker="#FFFFFF"
        vertex="#FFFFFF"
        vertex_select="#FFFFFF"
        vertex_active="#FFFFFF"
        vertex_size="3"
        vertex_bevel="#FFFFFF"
        vertex_unreferenced="#FFFFFF"
        edge_select="#FFFFFF"
        edge_seam="#FFFFFF"
        edge_sharp="#FFFFFF"
        edge_crease="#FFFFFF"
        edge_bevel="#FFFFFF"
        edge_facesel="#FFFFFF"
        freestyle_edge_mark="#FFFFFF"
        face="#FFFFFF"
        face_select="#FFFFFF"
        face_dot="#FFFFFF"
        facedot_size="3"
        freestyle_face_mark="#FFFFFF"
        face_back="#FFFFFF"
        face_front="#FFFFFF"
        nurb_uline="#FFFFFF"
        nurb_vline="#FFFFFF"
        nurb_sel_uline="#FFFFFF"
        nurb_sel_vline="#FFFFFF"
        act_spline="#FFFFFF"
        handle_free="#FFFFFF"
        handle_auto="#FFFFFF"
        handle_vect="#FFFFFF"
        handle_sel_vect="#FFFFFF"
        handle_align="#FFFFFF"
        handle_sel_free="#FFFFFF"
        handle_sel_auto="#FFFFFF"
        handle_sel_align="#FFFFFF"
        lastsel_point="#FFFFFF"
        extra_edge_len="#FFFFFF"
        extra_edge_angle="#FFFFFF"
        extra_face_angle="#FFFFFF"
        extra_face_area="#FFFFFF"
        editmesh_active="#FFFFFF"
        normal="#FFFFFF"
        vertex_normal="#FFFFFF"
        split_normal="#FFFFFF"
        bone_pose="#FFFFFF"
        bone_pose_active="#FFFFFF"
        bone_solid="#FFFFFF"
        bone_locked_weight="#FFFFFF"
        bundle_solid="#FFFFFF"
        camera_path="#FFFFFF"
        camera_passepartout="#FFFFFF"
        skin_root="#FFFFFF"
        view_overlay="#FFFFFF"
        transform="#FFFFFF"
        frame_current="#FFFFFF"
        paint_curve_handle="#FFFFFF"
        paint_curve_pivot="#FFFFFF"
        outline_width="1"
        object_origin_size="6"
        >
        <space>
          <ThemeSpaceGradient
            title="#FFFFFF"
            text="#FFFFFF"
            text_hi="#FFFFFF"
            header="#FFFFFF"
            header_text="#FFFFFF"
            header_text_hi="#FFFFFF"
            button="#FFFFFF"
            button_title="#FFFFFF"
            button_text="#FFFFFF"
            button_text_hi="#FFFFFF"
            navigation_bar="#FFFFFF"
            execution_buts="#FFFFFF"
            tab_active="#FFFFFF"
            tab_inactive="#FFFFFF"
            tab_back="#FFFFFF"
            tab_outline="#FFFFFF"
            >
            <gradients>
              <ThemeGradientColors
                background_type="RADIAL"
                high_gradient="#FFFFFF"
                gradient="#FFFFFF"
                >
              </ThemeGradientColors>
            </gradients>
            <panelcolors>
              <ThemePanelColors
                header="#FFFFFF"
                back="#FFFFFF"
                sub_back="#FFFFFF"
                >
              </ThemePanelColors>
            </panelcolors>
          </ThemeSpaceGradient>
        </space>
      </ThemeView3D>
    </view_3d>
    <graph_editor>
      <ThemeGraphEditor
        grid="#FFFFFF"
        frame_current="#FFFFFF"
        time_scrub_background="#FFFFFF"
        time_marker_line="#FFFFFF"
        time_marker_line_selected="#FFFFFF"
        window_sliders="#FFFFFF"
        channels_region="#FFFFFF"
        dopesheet_channel="#FFFFFF"
        dopesheet_subchannel="#FFFFFF"
        channel_group="#FFFFFF"
        active_channels_group="#FFFFFF"
        preview_range="#FFFFFF"
        vertex="#FFFFFF"
        vertex_select="#FFFFFF"
        vertex_active="#FFFFFF"
        vertex_size="10"
        vertex_bevel="#FFFFFF"
        vertex_unreferenced="#FFFFFF"
        handle_free="#FFFFFF"
        handle_auto="#FFFFFF"
        handle_vect="#FFFFFF"
        handle_sel_vect="#FFFFFF"
        handle_align="#FFFFFF"
        handle_sel_free="#FFFFFF"
        handle_sel_auto="#FFFFFF"
        handle_sel_align="#FFFFFF"
        handle_auto_clamped="#FFFFFF"
        handle_sel_auto_clamped="#FFFFFF"
        lastsel_point="#FFFFFF"
        handle_vertex="#FFFFFF"
        handle_vertex_select="#FFFFFF"
        handle_vertex_size="8"
        >
        <space>
          <ThemeSpaceGeneric
            back="#FFFFFF"
            title="#FFFFFF"
            text="#FFFFFF"
            text_hi="#FFFFFF"
            header="#FFFFFF"
            header_text="#FFFFFF"
            header_text_hi="#FFFFFF"
            button="#FFFFFF"
            button_title="#FFFFFF"
            button_text="#FFFFFF"
            button_text_hi="#FFFFFF"
            navigation_bar="#FFFFFF"
            execution_buts="#FFFFFF"
            tab_active="#FFFFFF"
            tab_inactive="#FFFFFF"
            tab_back="#FFFFFF"
            tab_outline="#FFFFFF"
            >
            <panelcolors>
              <ThemePanelColors
                header="#FFFFFF"
                back="#FFFFFF"
                sub_back="#FFFFFF"
                >
              </ThemePanelColors>
            </panelcolors>
          </ThemeSpaceGeneric>
        </space>
        <space_list>
          <ThemeSpaceListGeneric
            list="#FFFFFF"
            list_title="#FFFFFF"
            list_text="#FFFFFF"
            list_text_hi="#FFFFFF"
            >
          </ThemeSpaceListGeneric>
        </space_list>
      </ThemeGraphEditor>
    </graph_editor>
    <file_browser>
      <ThemeFileBrowser
        selected_file="#FFFFFF"
        row_alternate="#FFFFFF"
        >
        <space>
          <ThemeSpaceGeneric
            back="#FFFFFF"
            title="#FFFFFF"
            text="#FFFFFF"
            text_hi="#FFFFFF"
            header="#FFFFFF"
            header_text="#FFFFFF"
            header_text_hi="#FFFFFF"
            button="#FFFFFF"
            button_title="#FFFFFF"
            button_text="#FFFFFF"
            button_text_hi="#FFFFFF"
            navigation_bar="#FFFFFF"
            execution_buts="#FFFFFF"
            tab_active="#FFFFFF"
            tab_inactive="#FFFFFF"
            tab_back="#FFFFFF"
            tab_outline="#FFFFFF"
            >
            <panelcolors>
              <ThemePanelColors
                header="#FFFFFF"
                back="#FFFFFF"
                sub_back="#FFFFFF"
                >
              </ThemePanelColors>
            </panelcolors>
          </ThemeSpaceGeneric>
        </space>
      </ThemeFileBrowser>
    </file_browser>
    <nla_editor>
      <ThemeNLAEditor
        grid="#FFFFFF"
        view_sliders="#FFFFFF"
        dopesheet_channel="#FFFFFF"
        nla_track="#FFFFFF"
        active_action="#FFFFFF"
        active_action_unset="#FFFFFF"
        preview_range="#FFFFFF"
        strips="#FFFFFF"
        strips_selected="#FFFFFF"
        transition_strips="#FFFFFF"
        transition_strips_selected="#FFFFFF"
        meta_strips="#FFFFFF"
        meta_strips_selected="#FFFFFF"
        sound_strips="#FFFFFF"
        sound_strips_selected="#FFFFFF"
        tweak="#FFFFFF"
        tweak_duplicate="#FFFFFF"
        keyframe_border="#FFFFFF"
        keyframe_border_selected="#FFFFFF"
        frame_current="#FFFFFF"
        time_scrub_background="#FFFFFF"
        time_marker_line="#FFFFFF"
        time_marker_line_selected="#FFFFFF"
        >
        <space>
          <ThemeSpaceGeneric
            back="#FFFFFF"
            title="#FFFFFF"
            text="#FFFFFF"
            text_hi="#FFFFFF"
            header="#FFFFFF"
            header_text="#FFFFFF"
            header_text_hi="#FFFFFF"
            button="#FFFFFF"
            button_title="#FFFFFF"
            button_text="#FFFFFF"
            button_text_hi="#FFFFFF"
            navigation_bar="#FFFFFF"
            execution_buts="#FFFFFF"
            tab_active="#FFFFFF"
            tab_inactive="#FFFFFF"
            tab_back="#FFFFFF"
            tab_outline="#FFFFFF"
            >
            <panelcolors>
              <ThemePanelColors
                header="#FFFFFF"
                back="#FFFFFF"
                sub_back="#FFFFFF"
                >
              </ThemePanelColors>
            </panelcolors>
          </ThemeSpaceGeneric>
        </space>
        <space_list>
          <ThemeSpaceListGeneric
            list="#FFFFFF"
            list_title="#FFFFFF"
            list_text="#FFFFFF"
            list_text_hi="#FFFFFF"
            >
          </ThemeSpaceListGeneric>
        </space_list>
      </ThemeNLAEditor>
    </nla_editor>
    <dopesheet_editor>
      <ThemeDopeSheet
        grid="#FFFFFF"
        frame_current="#FFFFFF"
        time_scrub_background="#FFFFFF"
        time_marker_line="#FFFFFF"
        time_marker_line_selected="#FFFFFF"
        value_sliders="#FFFFFF"
        view_sliders="#FFFFFF"
        dopesheet_channel="#FFFFFF"
        dopesheet_subchannel="#FFFFFF"
        channels="#FFFFFF"
        channels_selected="#FFFFFF"
        channel_group="#FFFFFF"
        active_channels_group="#FFFFFF"
        long_key="#FFFFFF"
        long_key_selected="#FFFFFF"
        keyframe="#FFFFFF"
        keyframe_selected="#FFFFFF"
        keyframe_extreme="#FFFFFF"
        keyframe_extreme_selected="#FFFFFF"
        keyframe_breakdown="#FFFFFF"
        keyframe_breakdown_selected="#FFFFFF"
        keyframe_jitter="#FFFFFF"
        keyframe_jitter_selected="#FFFFFF"
        keyframe_movehold="#FFFFFF"
        keyframe_movehold_selected="#FFFFFF"
        keyframe_border="#FFFFFF"
        keyframe_border_selected="#FFFFFF"
        keyframe_scale_factor="1"
        summary="#FFFFFF"
        preview_range="#FFFFFF"
        interpolation_line="#FFFFFF"
        >
        <space>
          <ThemeSpaceGeneric
            back="#FFFFFF"
            title="#FFFFFF"
            text="#FFFFFF"
            text_hi="#FFFFFF"
            header="#FFFFFF"
            header_text="#FFFFFF"
            header_text_hi="#FFFFFF"
            button="#FFFFFF"
            button_title="#FFFFFF"
            button_text="#FFFFFF"
            button_text_hi="#FFFFFF"
            navigation_bar="#FFFFFF"
            execution_buts="#FFFFFF"
            tab_active="#FFFFFF"
            tab_inactive="#FFFFFF"
            tab_back="#FFFFFF"
            tab_outline="#FFFFFF"
            >
            <panelcolors>
              <ThemePanelColors
                header="#FFFFFF"
                back="#FFFFFF"
                sub_back="#FFFFFF"
                >
              </ThemePanelColors>
            </panelcolors>
          </ThemeSpaceGeneric>
        </space>
        <space_list>
          <ThemeSpaceListGeneric
            list="#FFFFFF"
            list_title="#FFFFFF"
            list_text="#FFFFFF"
            list_text_hi="#FFFFFF"
            >
          </ThemeSpaceListGeneric>
        </space_list>
      </ThemeDopeSheet>
    </dopesheet_editor>
    <image_editor>
      <ThemeImageEditor
        grid="#FFFFFF"
        vertex="#FFFFFF"
        vertex_select="#FFFFFF"
        vertex_active="#FFFFFF"
        vertex_size="3"
        vertex_bevel="#FFFFFF"
        vertex_unreferenced="#FFFFFF"
        face="#FFFFFF"
        face_select="#FFFFFF"
        face_dot="#FFFFFF"
        facedot_size="3"
        freestyle_face_mark="#FFFFFF"
        face_back="#FFFFFF"
        face_front="#FFFFFF"
        editmesh_active="#FFFFFF"
        wire_edit="#FFFFFF"
        edge_width="1"
        edge_select="#FFFFFF"
        scope_back="#FFFFFF"
        preview_stitch_face="#FFFFFF"
        preview_stitch_edge="#FFFFFF"
        preview_stitch_vert="#FFFFFF"
        preview_stitch_stitchable="#FFFFFF"
        preview_stitch_unstitchable="#FFFFFF"
        preview_stitch_active="#FFFFFF"
        uv_shadow="#FFFFFF"
        frame_current="#FFFFFF"
        metadatabg="#FFFFFF"
        metadatatext="#FFFFFF"
        handle_free="#FFFFFF"
        handle_auto="#FFFFFF"
        handle_align="#FFFFFF"
        handle_sel_free="#FFFFFF"
        handle_sel_auto="#FFFFFF"
        handle_sel_align="#FFFFFF"
        handle_auto_clamped="#FFFFFF"
        handle_sel_auto_clamped="#FFFFFF"
        handle_vertex="#FFFFFF"
        handle_vertex_select="#FFFFFF"
        handle_vertex_size="5"
        paint_curve_handle="#FFFFFF"
        paint_curve_pivot="#FFFFFF"
        >
        <space>
          <ThemeSpaceGeneric
            back="#FFFFFF"
            title="#FFFFFF"
            text="#FFFFFF"
            text_hi="#FFFFFF"
            header="#FFFFFF"
            header_text="#FFFFFF"
            header_text_hi="#FFFFFF"
            button="#FFFFFF"
            button_title="#FFFFFF"
            button_text="#FFFFFF"
            button_text_hi="#FFFFFF"
            navigation_bar="#FFFFFF"
            execution_buts="#FFFFFF"
            tab_active="#FFFFFF"
            tab_inactive="#FFFFFF"
            tab_back="#FFFFFF"
            tab_outline="#FFFFFF"
            >
            <panelcolors>
              <ThemePanelColors
                header="#FFFFFF"
                back="#FFFFFF"
                sub_back="#FFFFFF"
                >
              </ThemePanelColors>
            </panelcolors>
          </ThemeSpaceGeneric>
        </space>
      </ThemeImageEditor>
    </image_editor>
    <sequence_editor>
      <ThemeSequenceEditor
        grid="#FFFFFF"
        window_sliders="#FFFFFF"
        movie_strip="#FFFFFF"
        movieclip_strip="#FFFFFF"
        image_strip="#FFFFFF"
        scene_strip="#FFFFFF"
        audio_strip="#FFFFFF"
        effect_strip="#FFFFFF"
        color_strip="#FFFFFF"
        meta_strip="#FFFFFF"
        mask_strip="#FFFFFF"
        text_strip="#FFFFFF"
        active_strip="#FFFFFF"
        selected_strip="#FFFFFF"
        frame_current="#FFFFFF"
        time_scrub_background="#FFFFFF"
        time_marker_line="#FFFFFF"
        time_marker_line_selected="#FFFFFF"
        keyframe="#FFFFFF"
        draw_action="#FFFFFF"
        preview_back="#FFFFFF"
        metadatabg="#FFFFFF"
        metadatatext="#FFFFFF"
        preview_range="#FFFFFF"
        row_alternate="#FFFFFF"
        >
        <space>
          <ThemeSpaceGeneric
            back="#FFFFFF"
            title="#FFFFFF"
            text="#FFFFFF"
            text_hi="#FFFFFF"
            header="#FFFFFF"
            header_text="#FFFFFF"
            header_text_hi="#FFFFFF"
            button="#FFFFFF"
            button_title="#FFFFFF"
            button_text="#FFFFFF"
            button_text_hi="#FFFFFF"
            navigation_bar="#FFFFFF"
            execution_buts="#FFFFFF"
            tab_active="#FFFFFF"
            tab_inactive="#FFFFFF"
            tab_back="#FFFFFF"
            tab_outline="#FFFFFF"
            >
            <panelcolors>
              <ThemePanelColors
                header="#FFFFFF"
                back="#FFFFFF"
                sub_back="#FFFFFF"
                >
              </ThemePanelColors>
            </panelcolors>
          </ThemeSpaceGeneric>
        </space>
        <space_list>
          <ThemeSpaceListGeneric
            list="#FFFFFF"
            list_title="#FFFFFF"
            list_text="#FFFFFF"
            list_text_hi="#FFFFFF"
            >
          </ThemeSpaceListGeneric>
        </space_list>
      </ThemeSequenceEditor>
    </sequence_editor>
    <properties>
      <ThemeProperties
        match="#FFFFFF"
        active_modifier="#FFFFFF"
        >
        <space>
          <ThemeSpaceGeneric
            back="#FFFFFF"
            title="#FFFFFF"
            text="#FFFFFF"
            text_hi="#FFFFFF"
            header="#FFFFFF"
            header_text="#FFFFFF"
            header_text_hi="#FFFFFF"
            button="#FFFFFF"
            button_title="#FFFFFF"
            button_text="#FFFFFF"
            button_text_hi="#FFFFFF"
            navigation_bar="#FFFFFF"
            execution_buts="#FFFFFF"
            tab_active="#FFFFFF"
            tab_inactive="#FFFFFF"
            tab_back="#FFFFFF"
            tab_outline="#FFFFFF"
            >
            <panelcolors>
              <ThemePanelColors
                header="#FFFFFF"
                back="#FFFFFF"
                sub_back="#FFFFFF"
                >
              </ThemePanelColors>
            </panelcolors>
          </ThemeSpaceGeneric>
        </space>
      </ThemeProperties>
    </properties>
    <text_editor>
      <ThemeTextEditor
        line_numbers="#FFFFFF"
        line_numbers_background="#FFFFFF"
        selected_text="#FFFFFF"
        cursor="#FFFFFF"
        syntax_builtin="#FFFFFF"
        syntax_symbols="#FFFFFF"
        syntax_special="#FFFFFF"
        syntax_preprocessor="#FFFFFF"
        syntax_reserved="#FFFFFF"
        syntax_comment="#FFFFFF"
        syntax_string="#FFFFFF"
        syntax_numbers="#FFFFFF"
        >
        <space>
          <ThemeSpaceGeneric
            back="#FFFFFF"
            title="#FFFFFF"
            text="#FFFFFF"
            text_hi="#FFFFFF"
            header="#FFFFFF"
            header_text="#FFFFFF"
            header_text_hi="#FFFFFF"
            button="#FFFFFF"
            button_title="#FFFFFF"
            button_text="#FFFFFF"
            button_text_hi="#FFFFFF"
            navigation_bar="#FFFFFF"
            execution_buts="#FFFFFF"
            tab_active="#FFFFFF"
            tab_inactive="#FFFFFF"
            tab_back="#FFFFFF"
            tab_outline="#FFFFFF"
            >
            <panelcolors>
              <ThemePanelColors
                header="#FFFFFF"
                back="#FFFFFF"
                sub_back="#FFFFFF"
                >
              </ThemePanelColors>
            </panelcolors>
          </ThemeSpaceGeneric>
        </space>
      </ThemeTextEditor>
    </text_editor>
    <node_editor>
      <ThemeNodeEditor
        grid="#FFFFFF"
        node_selected="#FFFFFF"
        node_active="#FFFFFF"
        wire="#FFFFFF"
        wire_inner="#FFFFFF"
        wire_select="#FFFFFF"
        selected_text="#FFFFFF"
        node_backdrop="#FFFFFF"
        converter_node="#FFFFFF"
        color_node="#FFFFFF"
        group_node="#FFFFFF"
        group_socket_node="#FFFFFF"
        frame_node="#FFFFFF"
        matte_node="#FFFFFF"
        distor_node="#FFFFFF"
        noodle_curving="4"
        grid_levels="3"
        dash_alpha="0.5"
        input_node="#FFFFFF"
        output_node="#FFFFFF"
        filter_node="#FFFFFF"
        vector_node="#FFFFFF"
        texture_node="#FFFFFF"
        shader_node="#FFFFFF"
        script_node="#FFFFFF"
        pattern_node="#FFFFFF"
        layout_node="#FFFFFF"
        geometry_node="#FFFFFF"
        attribute_node="#FFFFFF"
        >
        <space>
          <ThemeSpaceGeneric
            back="#FFFFFF"
            title="#FFFFFF"
            text="#FFFFFF"
            text_hi="#FFFFFF"
            header="#FFFFFF"
            header_text="#FFFFFF"
            header_text_hi="#FFFFFF"
            button="#FFFFFF"
            button_title="#FFFFFF"
            button_text="#FFFFFF"
            button_text_hi="#FFFFFF"
            navigation_bar="#FFFFFF"
            execution_buts="#FFFFFF"
            tab_active="#FFFFFF"
            tab_inactive="#FFFFFF"
            tab_back="#FFFFFF"
            tab_outline="#FFFFFF"
            >
            <panelcolors>
              <ThemePanelColors
                header="#FFFFFF"
                back="#FFFFFF"
                sub_back="#FFFFFF"
                >
              </ThemePanelColors>
            </panelcolors>
          </ThemeSpaceGeneric>
        </space>
        <space_list>
          <ThemeSpaceListGeneric
            list="#FFFFFF"
            list_title="#FFFFFF"
            list_text="#FFFFFF"
            list_text_hi="#FFFFFF"
            >
          </ThemeSpaceListGeneric>
        </space_list>
      </ThemeNodeEditor>
    </node_editor>
    <outliner>
      <ThemeOutliner
        match="#FFFFFF"
        selected_highlight="#FFFFFF"
        active="#FFFFFF"
        selected_object="#FFFFFF"
        active_object="#FFFFFF"
        edited_object="#FFFFFF"
        row_alternate="#FFFFFF"
        >
        <space>
          <ThemeSpaceGeneric
            back="#FFFFFF"
            title="#FFFFFF"
            text="#FFFFFF"
            text_hi="#FFFFFF"
            header="#FFFFFF"
            header_text="#FFFFFF"
            header_text_hi="#FFFFFF"
            button="#FFFFFF"
            button_title="#FFFFFF"
            button_text="#FFFFFF"
            button_text_hi="#FFFFFF"
            navigation_bar="#FFFFFF"
            execution_buts="#FFFFFF"
            tab_active="#FFFFFF"
            tab_inactive="#FFFFFF"
            tab_back="#FFFFFF"
            tab_outline="#FFFFFF"
            >
            <panelcolors>
              <ThemePanelColors
                header="#FFFFFF"
                back="#FFFFFF"
                sub_back="#FFFFFF"
                >
              </ThemePanelColors>
            </panelcolors>
          </ThemeSpaceGeneric>
        </space>
      </ThemeOutliner>
    </outliner>
    <info>
      <ThemeInfo
        info_selected="#FFFFFF"
        info_selected_text="#FFFFFF"
        info_error="#FFFFFF"
        info_error_text="#FFFFFF"
        info_warning="#FFFFFF"
        info_warning_text="#FFFFFF"
        info_info="#FFFFFF"
        info_info_text="#FFFFFF"
        info_debug="#FFFFFF"
        info_debug_text="#FFFFFF"
        info_property="#FFFFFF"
        info_property_text="#FFFFFF"
        info_operator="#FFFFFF"
        info_operator_text="#FFFFFF"
        >
        <space>
          <ThemeSpaceGeneric
            back="#FFFFFF"
            title="#FFFFFF"
            text="#FFFFFF"
            text_hi="#FFFFFF"
            header="#FFFFFF"
            header_text="#FFFFFF"
            header_text_hi="#FFFFFF"
            button="#FFFFFF"
            button_title="#FFFFFF"
            button_text="#FFFFFF"
            button_text_hi="#FFFFFF"
            navigation_bar="#FFFFFF"
            execution_buts="#FFFFFF"
            tab_active="#FFFFFF"
            tab_inactive="#FFFFFF"
            tab_back="#FFFFFF"
            tab_outline="#FFFFFF"
            >
            <panelcolors>
              <ThemePanelColors
                header="#FFFFFF"
                back="#FFFFFF"
                sub_back="#FFFFFF"
                >
              </ThemePanelColors>
            </panelcolors>
          </ThemeSpaceGeneric>
        </space>
      </ThemeInfo>
    </info>
    <preferences>
      <ThemePreferences>
        <space>
          <ThemeSpaceGeneric
            back="#FFFFFF"
            title="#FFFFFF"
            text="#FFFFFF"
            text_hi="#FFFFFF"
            header="#FFFFFF"
            header_text="#FFFFFF"
            header_text_hi="#FFFFFF"
            button="#FFFFFF"
            button_title="#FFFFFF"
            button_text="#FFFFFF"
            button_text_hi="#FFFFFF"
            navigation_bar="#FFFFFF"
            execution_buts="#FFFFFF"
            tab_active="#FFFFFF"
            tab_inactive="#FFFFFF"
            tab_back="#FFFFFF"
            tab_outline="#FFFFFF"
            >
            <panelcolors>
              <ThemePanelColors
                header="#FFFFFF"
                back="#FFFFFF"
                sub_back="#FFFFFF"
                >
              </ThemePanelColors>
            </panelcolors>
          </ThemeSpaceGeneric>
        </space>
      </ThemePreferences>
    </preferences>
    <console>
      <ThemeConsole
        line_output="#FFFFFF"
        line_input="#FFFFFF"
        line_info="#FFFFFF"
        line_error="#FFFFFF"
        cursor="#FFFFFF"
        select="#FFFFFF"
        >
        <space>
          <ThemeSpaceGeneric
            back="#FFFFFF"
            title="#FFFFFF"
            text="#FFFFFF"
            text_hi="#FFFFFF"
            header="#FFFFFF"
            header_text="#FFFFFF"
            header_text_hi="#FFFFFF"
            button="#FFFFFF"
            button_title="#FFFFFF"
            button_text="#FFFFFF"
            button_text_hi="#FFFFFF"
            navigation_bar="#FFFFFF"
            execution_buts="#FFFFFF"
            tab_active="#FFFFFF"
            tab_inactive="#FFFFFF"
            tab_back="#FFFFFF"
            tab_outline="#FFFFFF"
            >
            <panelcolors>
              <ThemePanelColors
                header="#FFFFFF"
                back="#FFFFFF"
                sub_back="#FFFFFF"
                >
              </ThemePanelColors>
            </panelcolors>
          </ThemeSpaceGeneric>
        </space>
      </ThemeConsole>
    </console>
    <clip_editor>
      <ThemeClipEditor
        grid="#FFFFFF"
        marker_outline="#FFFFFF"
        marker="#FFFFFF"
        active_marker="#FFFFFF"
        selected_marker="#FFFFFF"
        disabled_marker="#FFFFFF"
        locked_marker="#FFFFFF"
        path_before="#FFFFFF"
        path_after="#FFFFFF"
        path_keyframe_before="#FFFFFF"
        path_keyframe_after="#FFFFFF"
        frame_current="#FFFFFF"
        time_scrub_background="#FFFFFF"
        time_marker_line="#FFFFFF"
        time_marker_line_selected="#FFFFFF"
        strips="#FFFFFF"
        strips_selected="#FFFFFF"
        metadatabg="#FFFFFF"
        metadatatext="#FFFFFF"
        handle_free="#FFFFFF"
        handle_auto="#FFFFFF"
        handle_align="#FFFFFF"
        handle_sel_free="#FFFFFF"
        handle_sel_auto="#FFFFFF"
        handle_sel_align="#FFFFFF"
        handle_auto_clamped="#FFFFFF"
        handle_sel_auto_clamped="#FFFFFF"
        handle_vertex="#FFFFFF"
        handle_vertex_select="#FFFFFF"
        handle_vertex_size="5"
        >
        <space>
          <ThemeSpaceGeneric
            back="#FFFFFF"
            title="#FFFFFF"
            text="#FFFFFF"
            text_hi="#FFFFFF"
            header="#FFFFFF"
            header_text="#FFFFFF"
            header_text_hi="#FFFFFF"
            button="#FFFFFF"
            button_title="#FFFFFF"
            button_text="#FFFFFF"
            button_text_hi="#FFFFFF"
            navigation_bar="#FFFFFF"
            execution_buts="#FFFFFF"
            tab_active="#FFFFFF"
            tab_inactive="#FFFFFF"
            tab_back="#FFFFFF"
            tab_outline="#FFFFFF"
            >
            <panelcolors>
              <ThemePanelColors
                header="#FFFFFF"
                back="#FFFFFF"
                sub_back="#FFFFFF"
                >
              </ThemePanelColors>
            </panelcolors>
          </ThemeSpaceGeneric>
        </space>
        <space_list>
          <ThemeSpaceListGeneric
            list="#FFFFFF"
            list_title="#FFFFFF"
            list_text="#FFFFFF"
            list_text_hi="#FFFFFF"
            >
          </ThemeSpaceListGeneric>
        </space_list>
      </ThemeClipEditor>
    </clip_editor>
    <topbar>
      <ThemeTopBar>
        <space>
          <ThemeSpaceGeneric
            back="#FFFFFF"
            title="#FFFFFF"
            text="#FFFFFF"
            text_hi="#FFFFFF"
            header="#FFFFFF"
            header_text="#FFFFFF"
            header_text_hi="#FFFFFF"
            button="#FFFFFF"
            button_title="#FFFFFF"
            button_text="#FFFFFF"
            button_text_hi="#FFFFFF"
            navigation_bar="#FFFFFF"
            execution_buts="#FFFFFF"
            tab_active="#FFFFFF"
            tab_inactive="#FFFFFF"
            tab_back="#FFFFFF"
            tab_outline="#FFFFFF"
            >
            <panelcolors>
              <ThemePanelColors
                header="#FFFFFF"
                back="#FFFFFF"
                sub_back="#FFFFFF"
                >
              </ThemePanelColors>
            </panelcolors>
          </ThemeSpaceGeneric>
        </space>
      </ThemeTopBar>
    </topbar>
    <statusbar>
      <ThemeStatusBar>
        <space>
          <ThemeSpaceGeneric
            back="#FFFFFF"
            title="#FFFFFF"
            text="#FFFFFF"
            text_hi="#FFFFFF"
            header="#FFFFFF"
            header_text="#FFFFFF"
            header_text_hi="#FFFFFF"
            button="#FFFFFF"
            button_title="#FFFFFF"
            button_text="#FFFFFF"
            button_text_hi="#FFFFFF"
            navigation_bar="#FFFFFF"
            execution_buts="#FFFFFF"
            tab_active="#FFFFFF"
            tab_inactive="#FFFFFF"
            tab_back="#FFFFFF"
            tab_outline="#FFFFFF"
            >
            <panelcolors>
              <ThemePanelColors
                header="#FFFFFF"
                back="#FFFFFF"
                sub_back="#FFFFFF"
                >
              </ThemePanelColors>
            </panelcolors>
          </ThemeSpaceGeneric>
        </space>
      </ThemeStatusBar>
    </statusbar>
    <spreadsheet>
      <ThemeSpreadsheet
        row_alternate="#FFFFFF"
        >
        <space>
          <ThemeSpaceGeneric
            back="#FFFFFF"
            title="#FFFFFF"
            text="#FFFFFF"
            text_hi="#FFFFFF"
            header="#FFFFFF"
            header_text="#FFFFFF"
            header_text_hi="#FFFFFF"
            button="#FFFFFF"
            button_title="#FFFFFF"
            button_text="#FFFFFF"
            button_text_hi="#FFFFFF"
            navigation_bar="#FFFFFF"
            execution_buts="#FFFFFF"
            tab_active="#FFFFFF"
            tab_inactive="#FFFFFF"
            tab_back="#FFFFFF"
            tab_outline="#FFFFFF"
            >
            <panelcolors>
              <ThemePanelColors
                header="#FFFFFF"
                back="#FFFFFF"
                sub_back="#FFFFFF"
                >
              </ThemePanelColors>
            </panelcolors>
          </ThemeSpaceGeneric>
        </space>
        <space_list>
          <ThemeSpaceListGeneric
            list="#FFFFFF"
            list_title="#FFFFFF"
            list_text="#FFFFFF"
            list_text_hi="#FFFFFF"
            >
          </ThemeSpaceListGeneric>
        </space_list>
      </ThemeSpreadsheet>
    </spreadsheet>
    <bone_color_sets>
      <ThemeBoneColorSet
        normal="#FFFFFF"
        select="#FFFFFF"
        active="#FFFFFF"
        show_colored_constraints="FALSE"
        >
      </ThemeBoneColorSet>
      <ThemeBoneColorSet
        normal="#FFFFFF"
        select="#FFFFFF"
        active="#FFFFFF"
        show_colored_constraints="FALSE"
        >
      </ThemeBoneColorSet>
      <ThemeBoneColorSet
        normal="#FFFFFF"
        select="#FFFFFF"
        active="#FFFFFF"
        show_colored_constraints="FALSE"
        >
      </ThemeBoneColorSet>
      <ThemeBoneColorSet
        normal="#FFFFFF"
        select="#FFFFFF"
        active="#FFFFFF"
        show_colored_constraints="FALSE"
        >
      </ThemeBoneColorSet>
      <ThemeBoneColorSet
        normal="#FFFFFF"
        select="#FFFFFF"
        active="#FFFFFF"
        show_colored_constraints="FALSE"
        >
      </ThemeBoneColorSet>
      <ThemeBoneColorSet
        normal="#FFFFFF"
        select="#FFFFFF"
        active="#FFFFFF"
        show_colored_constraints="FALSE"
        >
      </ThemeBoneColorSet>
      <ThemeBoneColorSet
        normal="#FFFFFF"
        select="#FFFFFF"
        active="#FFFFFF"
        show_colored_constraints="FALSE"
        >
      </ThemeBoneColorSet>
      <ThemeBoneColorSet
        normal="#FFFFFF"
        select="#FFFFFF"
        active="#FFFFFF"
        show_colored_constraints="FALSE"
        >
      </ThemeBoneColorSet>
      <ThemeBoneColorSet
        normal="#FFFFFF"
        select="#FFFFFF"
        active="#FFFFFF"
        show_colored_constraints="FALSE"
        >
      </ThemeBoneColorSet>
      <ThemeBoneColorSet
        normal="#FFFFFF"
        select="#FFFFFF"
        active="#FFFFFF"
        show_colored_constraints="FALSE"
        >
      </ThemeBoneColorSet>
      <ThemeBoneColorSet
        normal="#FFFFFF"
        select="#FFFFFF"
        active="#FFFFFF"
        show_colored_constraints="FALSE"
        >
      </ThemeBoneColorSet>
      <ThemeBoneColorSet
        normal="#FFFFFF"
        select="#FFFFFF"
        active="#FFFFFF"
        show_colored_constraints="FALSE"
        >
      </ThemeBoneColorSet>
      <ThemeBoneColorSet
        normal="#FFFFFF"
        select="#FFFFFF"
        active="#FFFFFF"
        show_colored_constraints="FALSE"
        >
      </ThemeBoneColorSet>
      <ThemeBoneColorSet
        normal="#FFFFFF"
        select="#FFFFFF"
        active="#FFFFFF"
        show_colored_constraints="FALSE"
        >
      </ThemeBoneColorSet>
      <ThemeBoneColorSet
        normal="#FFFFFF"
        select="#FFFFFF"
        active="#FFFFFF"
        show_colored_constraints="FALSE"
        >
      </ThemeBoneColorSet>
      <ThemeBoneColorSet
        normal="#FFFFFF"
        select="#FFFFFF"
        active="#FFFFFF"
        show_colored_constraints="FALSE"
        >
      </ThemeBoneColorSet>
      <ThemeBoneColorSet
        normal="#FFFFFF"
        select="#FFFFFF"
        active="#FFFFFF"
        show_colored_constraints="FALSE"
        >
      </ThemeBoneColorSet>
      <ThemeBoneColorSet
        normal="#FFFFFF"
        select="#FFFFFF"
        active="#FFFFFF"
        show_colored_constraints="FALSE"
        >
      </ThemeBoneColorSet>
      <ThemeBoneColorSet
        normal="#FFFFFF"
        select="#FFFFFF"
        active="#FFFFFF"
        show_colored_constraints="FALSE"
        >
      </ThemeBoneColorSet>
      <ThemeBoneColorSet
        normal="#FFFFFF"
        select="#FFFFFF"
        active="#FFFFFF"
        show_colored_constraints="FALSE"
        >
      </ThemeBoneColorSet>
    </bone_color_sets>
    <collection_color>
      <ThemeCollectionColor
        color="#FFFFFF"
        >
      </ThemeCollectionColor>
      <ThemeCollectionColor
        color="#FFFFFF"
        >
      </ThemeCollectionColor>
      <ThemeCollectionColor
        color="#FFFFFF"
        >
      </ThemeCollectionColor>
      <ThemeCollectionColor
        color="#FFFFFF"
        >
      </ThemeCollectionColor>
      <ThemeCollectionColor
        color="#FFFFFF"
        >
      </ThemeCollectionColor>
      <ThemeCollectionColor
        color="#FFFFFF"
        >
      </ThemeCollectionColor>
      <ThemeCollectionColor
        color="#FFFFFF"
        >
      </ThemeCollectionColor>
      <ThemeCollectionColor
        color="#FFFFFF"
        >
      </ThemeCollectionColor>
    </collection_color>
    <strip_color>
      <ThemeStripColor
        color="#FFFFFF"
        >
      </ThemeStripColor>
      <ThemeStripColor
        color="#FFFFFF"
        >
      </ThemeStripColor>
      <ThemeStripColor
        color="#FFFFFF"
        >
      </ThemeStripColor>
      <ThemeStripColor
        color="#FFFFFF"
        >
      </ThemeStripColor>
      <ThemeStripColor
        color="#FFFFFF"
        >
      </ThemeStripColor>
      <ThemeStripColor
        color="#FFFFFF"
        >
      </ThemeStripColor>
      <ThemeStripColor
        color="#FFFFFF"
        >
      </ThemeStripColor>
      <ThemeStripColor
        color="#FFFFFF"
        >
      </ThemeStripColor>
      <ThemeStripColor
        color="#FFFFFF"
        >
      </ThemeStripColor>
    </strip_color>
  </Theme>
  <ThemeStyle>
    <panel_title>
      <ThemeFontStyle
        points="11"
        shadow="0"
        shadow_offset_x="0"
        shadow_offset_y="0"
        shadow_alpha="0"
        shadow_value="0"
        >
      </ThemeFontStyle>
    </panel_title>
    <widget_label>
      <ThemeFontStyle
        points="11"
        shadow="3"
        shadow_offset_x="0"
        shadow_offset_y="0"
        shadow_alpha="0"
        shadow_value="0"
        >
      </ThemeFontStyle>
    </widget_label>
    <widget>
      <ThemeFontStyle
        points="11"
        shadow="1"
        shadow_offset_x="0"
        shadow_offset_y="0"
        shadow_alpha="0"
        shadow_value="0"
        >
      </ThemeFontStyle>
    </widget>
  </ThemeStyle>
</bpy>
